{
  "date": "2025-09-22T22:00:00.000Z",
  "headings": "REPERTORIO del Coro",
  "picture": "",
  "description": "",
  "allegati": [
    {
      "lang": "it",
      "title": "Repertorio del Coro al 23.09.2025",
      "fileUrl": "/docs/brani-coro-al-29.09.2025.pdf"
    }
  ],
  "short_title": "REPERTORIO del Coro",
  "short_description": "",
  "links": [
    {
      "lang": "it",
      "linkUrl": "https://youtu.be/KjkdAReF6-4",
      "title": "Edizione 2016 (Video)"
    },
    {
      "lang": "en",
      "title": "2016 Edition (Video)",
      "linkUrl": "https://www.youtube.com/watch?v=Sn5RKHlHiYU&feature=share"
    },
    {
      "lang": "de",
      "linkUrl": "https://www.youtube.com/watch?v=2KavJ07f4z4",
      "title": "Wettbewerb 2016 (Video)"
    },
    {
      "lang": "es",
      "title": "Concurso 2016 (video)",
      "linkUrl": "https://youtu.be/9K89p3wg34E"
    }
  ]
}